constrained_gb/__init__.py
constrained_gb-0.1.3.dist-info/LICENSE
constrained_gb-0.1.3.dist-info/METADATA
constrained_gb-0.1.3.dist-info/WHEEL
constrained_gb-0.1.3.dist-info/top_level.txt
constrained_gb-0.1.3.dist-info/RECORD
