Metadata-Version: 2.1
Name: constrained-gb
Version: 0.1.3
Summary: constrained optimization for gradient boosting models with non-decomposable constraints
Home-page: https://github.com/maryami66/constrained_gb
Author: Maryam Bahrami
Author-email: maryami_66@yahoo.com
License: GNU General Public License v3 or later (GPLv3+)
Keywords: constrained optimization,gradient boosting
Platform: UNKNOWN
Classifier: Programming Language :: Python :: 3.6
Classifier: License :: OSI Approved :: GNU Affero General Public License v3 or later (AGPLv3+)
Classifier: Operating System :: OS Independent
Requires-Python: >=3.6
License-File: LICENSE
Requires-Dist: scikit-learn (>=0.22.0)
Requires-Dist: GPyOpt
Requires-Dist: numpy (>=1.19.3)
Requires-Dist: scipy (>=1.4.1)
Requires-Dist: matplotlib (>=3.2.1)
Requires-Dist: future
